trendshift/__init__.py
trendshift/trendshift.py
trendshift-0.5.0.dist-info/LICENSE.txt
trendshift-0.5.0.dist-info/METADATA
trendshift-0.5.0.dist-info/WHEEL
trendshift-0.5.0.dist-info/top_level.txt
trendshift-0.5.0.dist-info/RECORD
