Metadata-Version: 2.1
Name: trendshift
Version: 0.5.0
Summary: TrendShift is a builder library that appends some trend related cumulative calculation information about a column onto given pandas DataFrame.
Home-page: https://github.com/westial/trendshift
Author: Jaume Mila Bea
Author-email: jaume@westial.com
Project-URL: Bug Tracker, https://github.com/westial/trendshift/issues
Classifier: Programming Language :: Python :: 3
Classifier: License :: OSI Approved :: GNU General Public License v3 (GPLv3)
Classifier: Operating System :: OS Independent
Requires-Python: >=3.6.2
License-File: LICENSE.txt
Requires-Dist: pandas
